unv/__init__.py
unv/deploy/.DS_Store
unv/deploy/__init__.py
unv/deploy/app.py
unv/deploy/bin.py
unv/deploy/manager.py
unv/deploy/settings.py
unv/deploy/tasks.py
unv/deploy/components/.DS_Store
unv/deploy/components/__init__.py
unv/deploy/components/python.py
unv/deploy/components/systemd.py
unv/deploy/components/app/__init__.py
unv/deploy/components/app/app.service
unv/deploy/components/app/app.sh
unv/deploy/components/app/ipv4.rules
unv/deploy/components/iptables/__init__.py
unv/deploy/components/iptables/app.service
unv/deploy/components/iptables/custom.rules
unv/deploy/components/iptables/ipv4.rules
unv/deploy/components/nginx/__init__.py
unv/deploy/components/nginx/ipv4.rules
unv/deploy/components/nginx/server.conf
unv/deploy/components/nginx/server.service
unv/deploy/components/postgres/__init__.py
unv/deploy/components/postgres/ipv4.rules
unv/deploy/components/postgres/pg_hba.conf
unv/deploy/components/postgres/postgresql.conf
unv/deploy/components/postgres/server.service
unv/deploy/components/redis/__init__.py
unv/deploy/components/redis/ipv4.rules
unv/deploy/components/redis/server.conf
unv/deploy/components/redis/server.service
unv/deploy/providers/__init__.py
unv/deploy/providers/vagrant.py
unv/deploy/providers/vultr.py
unv.deploy-0.5.2.dist-info/LICENSE
unv.deploy-0.5.2.dist-info/METADATA
unv.deploy-0.5.2.dist-info/WHEEL
unv.deploy-0.5.2.dist-info/entry_points.txt
unv.deploy-0.5.2.dist-info/top_level.txt
unv.deploy-0.5.2.dist-info/zip-safe
unv.deploy-0.5.2.dist-info/RECORD
